cutword/__init__.py
cutword/comparewithjieba.py
cutword/cutword.py
cutword/dict.txt
cutword/model_ner.py
cutword/model_params.pth
cutword/ner.py
cutword/ner_vocab_tags.json
cutword/preprocess_data_final.json
cutword/pytorchcrf.py
cutword/unionwords.txt
cutword-0.1.1.dist-info/LICENSE
cutword-0.1.1.dist-info/METADATA
cutword-0.1.1.dist-info/WHEEL
cutword-0.1.1.dist-info/top_level.txt
cutword-0.1.1.dist-info/RECORD
