Metadata-Version: 2.1
Name: cutword
Version: 0.1.1
Summary: Just Cut Word Faster
Home-page: https://github.com/liwenju0/cutword
Author: liwenju
Author-email: liwenjudetiankong@126.com
License: Apache License 2.0
Requires-Python: >=3
License-File: LICENSE
Requires-Dist: numpy
Requires-Dist: tqdm
Requires-Dist: pyahocorasick
